restfulengine.py
setup.cfg
setup.py
restfulengine.egg-info/PKG-INFO
restfulengine.egg-info/SOURCES.txt
restfulengine.egg-info/dependency_links.txt
restfulengine.egg-info/requires.txt
restfulengine.egg-info/top_level.txt