Metadata-Version: 1.0
Name: restfulengine
Version: 1.0.1
Summary: Python client for the Windward RESTful Engine
Home-page: http://www.windward.net/products/restful/
Author: Windward Studios
Author-email: support@windward.net
License: UNKNOWN
Platform: UNKNOWN
